arq_http/__init__.py
arq_http/api.py
arq_http/config.py
arq_http/dashboard.py
arq_http/server.py
arq_http/stats.py
arq_http/utils.py
arq_http/worker.py
arq_http/frontend/assets/htmx-ext-sse-2.2.2.js
arq_http/frontend/assets/htmx.org-2.0.4.js
arq_http/frontend/assets/rapidoc-min.js
arq_http/frontend/assets/simple-datatables-6.0.8.js
arq_http/frontend/assets/style.css
arq_http/frontend/assets/terminal-0.7.4.min.css
arq_http/frontend/assets/uPlot.iife.min.js
arq_http/frontend/assets/uPlot.min.css
arq_http/frontend/templates/base.html.jinja
arq_http/frontend/templates/dashboard.html.jinja
arq_http/frontend/templates/dashboard_listing.html.jinja
arq_http/frontend/templates/docs.html.jinja
arq_http/frontend/templates/components/histogram.js.jinja
arq_http/frontend/templates/components/noplotdata.html.jinja
arq_http/frontend/templates/components/stats.html.jinja
arq_http/frontend/templates/components/table.html.jinja
arq_http/frontend/templates/components/table.js.jinja
arq_http/frontend/templates/components/timeseries.js.jinja
arq_http-0.2.data/scripts/arq-http
arq_http-0.2.dist-info/LICENSE
arq_http-0.2.dist-info/METADATA
arq_http-0.2.dist-info/WHEEL
arq_http-0.2.dist-info/top_level.txt
arq_http-0.2.dist-info/RECORD
