Metadata-Version: 2.2
Name: arq-http
Version: 0.2
Summary: arq dashboard and http api
Author: Piotr Patrzyk
License: MIT
Project-URL: Source, https://github.com/ppatrzyk/arq-http
Keywords: arq,dashboard,httping
Classifier: Development Status :: 4 - Beta
Classifier: License :: OSI Approved :: MIT License
Classifier: Operating System :: OS Independent
Classifier: Programming Language :: Python :: 3
Classifier: Topic :: Internet
Requires-Python: >=3.12
License-File: LICENSE
Requires-Dist: anyio==4.8.0
Requires-Dist: arq==0.26.3
Requires-Dist: click==8.1.8
Requires-Dist: h11==0.14.0
Requires-Dist: hiredis==3.1.0
Requires-Dist: idna==3.10
Requires-Dist: Jinja2==3.1.5
Requires-Dist: MarkupSafe==3.0.2
Requires-Dist: numpy==2.2.2
Requires-Dist: PyYAML==6.0.2
Requires-Dist: redis==5.2.1
Requires-Dist: sniffio==1.3.1
Requires-Dist: sse-starlette==2.2.1
Requires-Dist: starlette==0.45.3
Requires-Dist: typing_extensions==4.12.2
Requires-Dist: uvicorn==0.34.0
